dainty/__init__.py
dainty/dainty.py
dainty/documentation.py
dainty/py.typed
dainty/static/style.css
dainty-0.6.1.dist-info/METADATA
dainty-0.6.1.dist-info/WHEEL
dainty-0.6.1.dist-info/RECORD
