Metadata-Version: 2.4
Name: dainty
Version: 0.6.1
Summary: Create HTML boilerplate from pydantic models
Author-email: gaardhus <tobias_gaardhus@hotmail.com>
Requires-Python: >=3.12
Requires-Dist: ipython>=8.18.1
Requires-Dist: pydantic[email]>=2.9.2
Requires-Dist: pyhtml-enhanced>=2.1.0
Requires-Dist: pytest>=8.3.3
